montocarlo_ol_circlearea/Areacalculate.py
montocarlo_ol_circlearea/__init__.py
montocarlo_ol_circlearea-0.0.1.dist-info/METADATA
montocarlo_ol_circlearea-0.0.1.dist-info/WHEEL
montocarlo_ol_circlearea-0.0.1.dist-info/top_level.txt
montocarlo_ol_circlearea-0.0.1.dist-info/RECORD
