Metadata-Version: 2.1
Name: montocarlo-ol-circlearea
Version: 0.0.1
Summary: A Python library for calculating area of overlapped region between 2 Circle using MontoCarlo method (Random Points)
Home-page: https://montocarlo-ol-circlearea.readthedocs.io/
Author: Sabareeswaran Shanmugam
Author-email: sabareeswarans11@gmail.com
License: MIT
Platform: UNKNOWN
Classifier: Intended Audience :: Developers
Classifier: License :: OSI Approved :: MIT License
Classifier: Programming Language :: Python
Classifier: Programming Language :: Python :: 3
Classifier: Programming Language :: Python :: 3.6
Classifier: Programming Language :: Python :: 3.7
Classifier: Programming Language :: Python :: 3.8
Classifier: Programming Language :: Python :: 3.9
Classifier: Operating System :: OS Independent
Requires-Dist: numpy
